iot_device_backbone_client/__init__.py
iot_device_backbone_client/async_base_client.py
iot_device_backbone_client/base_model.py
iot_device_backbone_client/client.py
iot_device_backbone_client/create_device_system_resource_metrics.py
iot_device_backbone_client/create_fire_incident.py
iot_device_backbone_client/enums.py
iot_device_backbone_client/exceptions.py
iot_device_backbone_client/input_types.py
iot_device_backbone_client/update_fire_incident.py
iot_device_backbone_client/who_am_i.py
iot_device_backbone_client-0.0.2.dist-info/METADATA
iot_device_backbone_client-0.0.2.dist-info/WHEEL
iot_device_backbone_client-0.0.2.dist-info/top_level.txt
iot_device_backbone_client-0.0.2.dist-info/RECORD
