Metadata-Version: 2.1
Name: iot-device-backbone-client
Version: 0.0.2
Summary: Python client to consume the CIOT Device Backbone GraphQL API
Author-email: Adriaan Knapen <adriaan@claimr.tools>
License: UNLICENSED
Requires-Dist: pydantic
Requires-Dist: httpx
Requires-Dist: websockets
